<?xml version="1.0" encoding="utf-8"?>
<Defs>
  <!-- planetarian -->

  <BackstoryDef ParentName="Solid">
    <defName>RTTS_planetarian_Childhood</defName>
    <title>unknown</title>
    <titleShort>unknown</titleShort>
    <slot>Childhood</slot>
    <description>[PAWN_nameDef] certainly had a childhood too,
      but it was so long ago that they themselves don't remember it well. </description>
  </BackstoryDef>

  <BackstoryDef ParentName="Solid">
    <defName>RTTS_planetarian_Adulthood</defName>
    <title>planetarian</title>
    <titleShort>planetarian</titleShort>
    <description>Through a mysterious twist of fate, [PAWN_nameDef] became a 'planetarian'.
      As a result, while becoming a being that transcends human limits both physically and mentally,
      they continue living in the present.</description>
    <slot>Adulthood</slot>
    <skillGains>
      <Shooting>-10</Shooting>
      <Melee>-10</Melee>
      <Animals>8</Animals>
      <Artistic>8</Artistic>
      <Social>8</Social>
    </skillGains>
  </BackstoryDef>

</Defs>
